plico_dm/__init__.py
plico_dm/__version__.py
plico_dm/calibration/__init__.py
plico_dm/calibration/abstract_calibration_manager.py
plico_dm/calibration/calibration_manager.py
plico_dm/calibration/in_memory_calibration_manager.py
plico_dm/client/__init__.py
plico_dm/client/abstract_deformable_mirror_client.py
plico_dm/client/deformable_mirror_client.py
plico_dm/client/simulated_deformable_mirror_client.py
plico_dm/types/__init__.py
plico_dm/types/deformable_mirror_status.py
plico_dm/types/modal_basis.py
plico_dm/utils/__init__.py
plico_dm/utils/constants.py
plico_dm/utils/timeout.py
plico_dm-1.1.0.dist-info/LICENSE
plico_dm-1.1.0.dist-info/METADATA
plico_dm-1.1.0.dist-info/WHEEL
plico_dm-1.1.0.dist-info/top_level.txt
plico_dm-1.1.0.dist-info/RECORD
