Metadata-Version: 2.1
Name: plico_dm
Version: 1.1.0
Summary: Interface to ALPAO and Boston MEMS deformable mirrors and Physik Instrumente tip tilt mirror
Home-page: https://github.com/lbusoni/plico_dm
Author: Lorenzo Busoni
Author-email: lorenzo.busoni@inaf.it
License: MIT
Keywords: plico, deformable mirror, ALPAO, Boston MEMS, Physik Instrument, piezo, laboratory, instrumentation control
Classifier: Development Status :: 4 - Beta
Classifier: Operating System :: POSIX :: Linux
Classifier: Programming Language :: Python :: 2.7
Classifier: Programming Language :: Python :: 3
License-File: LICENSE
Requires-Dist: plico >=0.28
Requires-Dist: numpy
Requires-Dist: six
Requires-Dist: astropy
